<?xml version="1.0" encoding="UTF-8"?>
<persistence version="2.0" xmlns="http://java.sun.com/xml/ns/persistence" xmlns:xsi="http://www.w3.org/2001/XMLSchema-instance" xsi:schemaLocation="http://java.sun.com/xml/ns/persistence http://java.sun.com/xml/ns/persistence/persistence_2_0.xsd">
	<persistence-unit name="DSNstock-PU">
		<class>fr.hsh.dsn.orm.entities.p02v02.T00</class>
		<class>fr.hsh.dsn.orm.entities.p02v02.T01</class>
		<class>fr.hsh.dsn.orm.entities.p02v02.T02</class>
		<class>fr.hsh.dsn.orm.entities.p02v02.T03</class>
		<class>fr.hsh.dsn.orm.entities.p02v02.T05</class>
		<class>fr.hsh.dsn.orm.entities.p02v02.T06</class>
		<class>fr.hsh.dsn.orm.entities.p02v02.T11</class>
		<class>fr.hsh.dsn.orm.entities.p02v02.T15</class>
		<class>fr.hsh.dsn.orm.entities.p02v02.T30</class>
		<class>fr.hsh.dsn.orm.entities.p02v02.T31</class>
		<class>fr.hsh.dsn.orm.entities.p02v02.T40</class>
		<class>fr.hsh.dsn.orm.entities.p02v02.T41</class>
		<class>fr.hsh.dsn.orm.entities.p02v02.T62</class>
		<class>fr.hsh.dsn.orm.entities.p02v02.T70</class>
		<class>fr.hsh.dsn.orm.entities.p02v02.T72</class>
		<class>fr.hsh.dsn.orm.entities.p02v02.T85</class>
		<class>fr.hsh.dsn.orm.entities.p02v02.T90</class>
		
		<class>fr.hsh.dsn.orm.entities.p03v03.T07</class>
		<class>fr.hsh.dsn.orm.entities.p03v03.T16</class>
		<class>fr.hsh.dsn.orm.entities.p03v03.T20</class>
		<class>fr.hsh.dsn.orm.entities.p03v03.T50</class>
		<class>fr.hsh.dsn.orm.entities.p03v03.T51</class>
		<class>fr.hsh.dsn.orm.entities.p03v03.T52</class>
		<class>fr.hsh.dsn.orm.entities.p03v03.T53</class>
		<class>fr.hsh.dsn.orm.entities.p03v03.T54</class>
		<class>fr.hsh.dsn.orm.entities.p03v03.T55</class>
		<class>fr.hsh.dsn.orm.entities.p03v03.T60</class>
		<class>fr.hsh.dsn.orm.entities.p03v03.T65</class>
		<class>fr.hsh.dsn.orm.entities.p03v03.T66</class>
		<class>fr.hsh.dsn.orm.entities.p03v03.T71</class>
		<class>fr.hsh.dsn.orm.entities.p03v03.T73</class>
		<class>fr.hsh.dsn.orm.entities.p03v03.T78</class>
		<class>fr.hsh.dsn.orm.entities.p03v03.T79</class>
		<class>fr.hsh.dsn.orm.entities.p03v03.T81</class>
		<class>fr.hsh.dsn.orm.entities.p03v03.T82</class>
		<class>fr.hsh.dsn.orm.entities.p03v03.T86</class>
	</persistence-unit>
</persistence>